LICENSE
README.md
setup.py
pypimdoc/__init__.py
pypimdoc/pypimdoc.py
pypimdoc.egg-info/PKG-INFO
pypimdoc.egg-info/SOURCES.txt
pypimdoc.egg-info/dependency_links.txt
pypimdoc.egg-info/entry_points.txt
pypimdoc.egg-info/top_level.txt