Metadata-Version: 2.2
Name: pypimdoc
Version: 1.1
Summary: A Python module for generating Python module documentation
Home-page: https://www.pg12.org/software
Author: A Andersen
Author-email: a.andersen@pg12.org
License: Modified BSD License
Project-URL: Download, https://www.pg12.org/dist/py/lib/pypimdoc/
Classifier: License :: OSI Approved :: BSD License
Classifier: Programming Language :: Python :: 3
Classifier: Operating System :: OS Independent
License-File: LICENSE
Dynamic: author
Dynamic: author-email
Dynamic: classifier
Dynamic: description
Dynamic: description-content-type
Dynamic: home-page
Dynamic: license
Dynamic: project-url
Dynamic: summary
